{
    "ProductType": [
        {
            "PutRequest": {
                "Item": {
                    "ProductTypeId": {"N": "100"},
                    "ProductTypeName": {"S": "PhotoBook"},
					"EffectiveStatusCode": {"N": "0"},
					"CreatedAt": {"S": "2022-01-21T12:06:00.064Z"},
					"CreatedBy": {"S": "user1"}
                }
            }
        },
        {
            "PutRequest": {
                "Item": {
                    "ProductTypeId": {"N": "101"},
                    "ProductTypeName": {"S": "Calendar"},
					"EffectiveStatusCode": {"N": "0"},
					"CreatedAt": {"S": "2022-01-21T12:06:00.064Z"},
					"CreatedBy": {"S": "user1"}
                }
            }
        },
        {
            "PutRequest": {
                "Item": {
                    "ProductTypeId": {"N": "102"},
                    "ProductTypeName": {"S": "Canvas"},
					"EffectiveStatusCode": {"N": "0"},
					"CreatedAt": {"S": "2022-01-21T12:06:00.064Z"},
					"CreatedBy": {"S": "user1"}
                }
            }
        },
		{
            "PutRequest": {
                "Item": {
                    "ProductTypeId": {"N": "103"},
                    "ProductTypeName": {"S": "Cards"},
					"EffectiveStatusCode": {"N": "0"},
					"CreatedAt": {"S": "2022-01-21T12:06:00.064Z"},
					"CreatedBy": {"S": "user1"}
                }
            }
        },
		{
            "PutRequest": {
                "Item": {
                    "ProductTypeId": {"N": "104"},
                    "ProductTypeName": {"S": "Mug"},
					"EffectiveStatusCode": {"N": "0"},
					"CreatedAt": {"S": "2022-01-21T12:06:00.064Z"},
					"CreatedBy": {"S": "user1"}
                }
            }
        }
    ]
}